{
  "paragraphs": [
    {
      "text": "በስመ አብ ብዬ እስቲ ሰላምታ ላድርስ\nለአብና ወወልድ ወመንፈስ ቅዱስ",
      "indent": 0
    },
    {
      "text": "እስቲ ላስታውስ የህማማቱን ሳምንት\nየጌታዬን የክርስቶስን ስቅለት",
      "indent": 24
    },
    {
      "text": "እንደዚህ ነው የመድኃኒዓለም መከራ\nያሰቅቃል በሰው አንደበት ሲወራ",
      "indent": 0
    },
    {
      "text": "አይሁድም በምቀኝነት ተነስተው\nመከሩበት ጌታን ለመግደል አሲረው",
      "indent": 24
    },
    {
      "text": "ከሐዋርያት አንዱን ይሁዳን ጠርተው\nከሱ ጋራ በሚስጥር መሐላ ምለው",
      "indent": 0
    },
    {
      "text": "ፈጣሪውን በመሳም ሊያሲዝ ጠቁሞ\nሊመራቸው የጌታን ጉንጮቹን ስሞ",
      "indent": 24
    },
    {
      "text": "ሰላሳ ብር የእጅ መንሻውን ሰጠው\nሊያሳያቸው ጌታውን ሄዶ ሳመው",
      "indent": 0
    },
    {
      "text": "ጌታም አውቆ ምነው ነከስከኝ አለው\nወይ ይሁዳ እንደምን ያለ ሰው ነው",
      "indent": 24
    },
    {
      "text": "ፈጣሪውን በሰላሳ ብር ሸጠው\nእንዲህ ነበር የህማማቱ ስቃይ",
      "indent": 0
    },
    {
      "text": "የሚያሰቅቅ በሰው አእምሮ ሲታይ\nሰኞ መክረው ማክሰኞም ዋሉ ሲያሴሩ",
      "indent": 24
    },
    {
      "text": "እሮብም አፅንተው በጣም መከሩ\nሀሙስ ሌሊት ይዘው የፊጥኝ አስረው",
      "indent": 0
    },
    {
      "text": "አቀረቡት ፍርድ አደባባይ ወስደው\nአስፈረዱ ሞት ይገባዋል ብለው",
      "indent": 24
    },
    {
      "text": "እየመቱ በትልቅ በትር መትሮት\nአቀዳጁት የአክሊለ እሾክን ብረት",
      "indent": 0
    },
    {
      "text": "የአይሁድ ንጉስ አንተ ነህ እንዴ እያሉ\nአፌዙበት ተሳለቁበት በሙሉ",
      "indent": 24
    },
    {
      "text": "ተረባርበው በግፍ ገረፉት ወስደው\nሳይበድል ወንጀለኛ ነህ ብለው",
      "indent": 0
    },
    {
      "text": "ሲያንገላቱት ሲደበድቡ በተራ\nአደረሱት ከቀራንዮ ተራራ",
      "indent": 24
    },
    {
      "text": "አሸክመው ከባዱን መስቀል በግፍ\nአሰቃዩት ፈጣሪያቸውን በግርፍ",
      "indent": 0
    },
    {
      "text": "በእለተ አርብ ስድስት ሰአት ሲሆን\nሰቀሉት የዓለም ብርሃን ጌታን",
      "indent": 24
    },
    {
      "text": "ነፍሱን ሰጠ ዘጠኝ ሰአት ሲሆን\nተናወጠ ምድርና ሰማይ በእውን",
      "indent": 0
    },
    {
      "text": "እርቃኑን መሆኑን አይታ ፀሐይ\nጨለመች ብርሃኗ ታጣ ከላይ",
      "indent": 24
    },
    {
      "text": "ከዋክብትም ከሰማይ ረግፈው አለቁ\nበቦታቸው አንድም ሳይተርፉ ወደቁ",
      "indent": 0
    },
    {
      "text": "ጨረቃዋ ብርሃኗን ነፍጋ ጨለመች\nፈጣሪዋ እርቃኑን ሆና ስላየች",
      "indent": 24
    },
    {
      "text": "መጋረጃው ከቤተ መቅደስ ያለው\nተቀደደ ከታች እስከላይ ወዲያው",
      "indent": 0
    },
    {
      "text": "ተሰቅሎም ዘጠኝ ሰአት ሲሆን\nተፈፀመ ብሎ አሰምቶ ቃሉን",
      "indent": 24
    },
    {
      "text": "ይህን ነግሮ ሞትን ቀመሰ መድኅን\nወደ ማታ ለንጊኖስ የሚባለው ሰው",
      "indent": 0
    },
    {
      "text": "የጌታን ጎን በተሳለ ጦር ወጋው\nቢወጋው ደምና ውሃ ፈሰሰ",
      "indent": 24
    },
    {
      "text": "የአዳምን ዘር በደሙ ፈሳሽ ቀደሰ\nውሃውም ለጥምቀታችን ሆነን",
      "indent": 0
    },
    {
      "text": "ስጋ ደሙን መዳኛ ብሎ ሰጠን\nብሉ ጠጡ ስጋዬንና ደሜን",
      "indent": 24
    },
    {
      "text": "ይህን ብሎ አንድነት አድርጎ ቸረን\nሁለት ሰዎች አረጋውያን ነበሩ",
      "indent": 0
    },
    {
      "text": "አወረዱ የጌታን ስጋ ሊቀብሩ\nገንዘው በሀዘንና በለቅሶ",
      "indent": 24
    },
    {
      "text": "እስኪነሳ መቃብር በሀይል አፍርሶ\nቀበሩት እጅግ በመራር ሐዘን",
      "indent": 0
    },
    {
      "text": "ስለሞተ የአለም መድኃኒት መድኅን\nቅዳሜም ተቀብሮ ዋለ ጌታም",
      "indent": 24
    },
    {
      "text": "በመሞቱ ሳይንቀሳቀስ ምንም\nእሁድ ሌሊት መግነዝ ፍቱልኝ ሳይል",
      "indent": 0
    },
    {
      "text": "ከሙታን እርሱ ተነሳ በኃይል\nስብሐት ለአብ ወወልድ ወመንፈስ ቅዱስ",
      "indent": 24
    },
    {
      "text": "ለዓለም እስከዘላለም ድረስ",
      "indent": 0
    }
  ]
}