{
  "paragraphs": [
    {
      "text": "እመኑ በልጁ\nነውና ቀኝ እጁ\nየእኛን ስጋ ለብሷል\nሊያድነን ተገልጧል\n...",
      "indent": 0
    },
    {
      "text": "ስለወጣ ከሕግ ትእዛዙን ተላልፎ\nአዳም በዲያብሎስ ኖረ ተሸንፎ\nክፉ ሰልጥኖበት ሳለ በመቃተት\nየሚያድነው ሲሻ አምላኩ መጣለት\n...",
      "indent": 0
    },
    {
      "text": "ቅድመ ዓለም ከአባቱ እንደተወለደ\nበዳግመኛ ልደት ከሰማይ ወረደ\nበልዕልና ያለው በትህትና መጣ\nጨለማውን ሊሽር የጽድቅ ፀሐይ ወጣ\n...",
      "indent": 0
    },
    {
      "text": "ዓለምን የያዘው በበረት ተገኘ\nሰውን የፈጠረ የሰው ልጅ ተሰኘ\nፍቅር ኃያል ወልድን ስቦት ከመንበሩ\nእንዲሁ ወደደን ተገለጠ ፍቅሩ\n...",
      "indent": 0
    },
    {
      "text": "ከተጠበበበት አዳምን ለመፍጠር\nእጅጉን በለጠ ለእኛ ያለው ፍቅር\nዘጠና ዘጠኙን በበረሃ ትቶ\nአማኑኤል ተባለ የእኛን ስጋ ነስቶ\n...",
      "indent": 0
    }
  ]
}