{
  "paragraphs": [
    {
      "text": "ዲያቢሎስን ከሁሉ በላይ አርጐት\nበብልጠት አምላክ የሚሆን መስሎት",
      "indent": 0
    },
    {
      "text": "ፈጠርኩ አለ ይኽንን ሁሉ ፍጥረት\nመላእክት ፈጥረህ አሳየን ቢሉት",
      "indent": 24
    },
    {
      "text": "ሊፈጥር እጁን ጨመረ ከእሳት\nእሳት አውቃ የዲያቢሎስን ትዕቢት",
      "indent": 0
    },
    {
      "text": "አረገችው እሳት የበላው ጅማት\nተባበሩ መላእክት ሁሉ ሊክዱ",
      "indent": 24
    },
    {
      "text": "የሰገዱ አብረውት ሲኦል ወረዱ\nጌታም አይቶ የእኩሌቶቹን ሀዘን",
      "indent": 0
    },
    {
      "text": "እሱ ክዶ ሳያስክዳቸው ሰይጣን\nለማመን ፈጠረላቸው ብርሃን",
      "indent": 24
    },
    {
      "text": "መላእክትም ይህንን ብርሃን አይተው\nሰገዱለት ቅዱስ እግዚአብሔር ብለው",
      "indent": 0
    },
    {
      "text": "በኹለት ቀን በተዠመረ ፍጥረት\nተናግረው ውሃውን ከሦስት",
      "indent": 24
    },
    {
      "text": "አንዱን ጠፈር አንዱንም ሐኖስ አሉት\nአንዱን ብቻ ከናጌብ ወዲያ ዳርቻ",
      "indent": 0
    },
    {
      "text": "ሠፈሩበት ሌዋትንና ብሄሞት\nበሦስት ቀን በተዠመረ ፍጥረት",
      "indent": 24
    },
    {
      "text": "ልታበቅል ምድር ሐመልማል ዘርፈ ቢላት\nአበቀለች ከአዝርዕት ጋር አትክልት",
      "indent": 0
    },
    {
      "text": "በዐራት ቀን እንዳይሠለጥን ጽልመት\nከከዋክብትም ከጨረቃ ጋር ሌሊት",
      "indent": 24
    },
    {
      "text": "በመዓልትም ፀሐይ ደገኛው ፍጥረት\nተፈጠሩ ለኛ ሊያበሩ በውነት",
      "indent": 0
    },
    {
      "text": "የኀሙስ ፍጥረት ገና እንደሆነ አይተው\nለታውፅኑ ባህር ዘመድ ዓሣት ብለው",
      "indent": 24
    },
    {
      "text": "የሚበርን የሚኼደውን በእግሩ\nለአንክሮ ለተዘክሮ ፈጠሩ",
      "indent": 0
    },
    {
      "text": "ዐርብ ጠዋት አዳም የኛን አባት\nንግበር ሰብ በአርአያ ቢሉት",
      "indent": 24
    },
    {
      "text": "ተፈጠረ ከመኸለኛው መሬት\nሥራውን በ6 ቀን ፈጽሞ",
      "indent": 0
    },
    {
      "text": "ዐረፈበት በ7ኛው ዕለት ደግሞ\nሥራችንን በ6 ቀን ሠርተን",
      "indent": 24
    },
    {
      "text": "እናንተም ከሥራ እረፉ ሲለን\nበፈጠሩት በስምንተኛው ዕለት",
      "indent": 0
    },
    {
      "text": "በሣልስት ብቻውን ሆኖ ቢያዩት\nንግበር ብለው ከጐኑ አንስተው አጥንት",
      "indent": 24
    },
    {
      "text": "ልትረዳው ሔዋንን ፈጥረው ሰጡት\nበአርባ ቀኑ ወስዶ አግብቶታል ገነት",
      "indent": 0
    },
    {
      "text": "አግብቶትም ወስኖለታል ስርዓት\nአትንካ ሲል ከዕፀ በለስ ቅንጣት",
      "indent": 24
    },
    {
      "text": "ብላ ጠጣ የቀረን ሁሉ ፍጥረት\nከምድር በላይ ከሰማይ በታች ያለው",
      "indent": 0
    },
    {
      "text": "ፍጥረት ሁሉ ላንተ ይገዛል አለው\nቢቀርብለት ዕፀ በለስን መብላት",
      "indent": 24
    },
    {
      "text": "ሳይታመም ከህመም በኋላም ሳይሞት\nሊያወርሰው የዲያቢሎስን ርስት",
      "indent": 0
    },
    {
      "text": "እንስሳት በሰባተኛው ዓመት\nአራዊትም አዳምን ሄደው አሉት",
      "indent": 24
    },
    {
      "text": "ወተትን እያለብክ ጠጣን ወለድን\nያልወለዱም እያረድክ ብላን ሰባን",
      "indent": 0
    },
    {
      "text": "አዳምም እንዲህ ይላቸው ዠመር\nእኔንማ እንዳያገኘኝ ችጋር",
      "indent": 24
    },
    {
      "text": "ሁሉን ብላ ከዕፀ በለስ በቀር\nብሎኝ የለን ለኔ ጌታዬ ጌታችሁ",
      "indent": 0
    },
    {
      "text": "እናንተንስ ባላችሁበት ያርባችሁ\nእናንተንስ ባላችሁበት ያስባችሁ",
      "indent": 24
    },
    {
      "text": "እንስሳትም ደስ እያላቸው ሲሄዱ\nየገነትን ተራራ ዐቀበት ወረዱ",
      "indent": 0
    },
    {
      "text": "ርስቱን አዳም የቀማው ሰይጣን\nእንስሳት ርቆላቸው ኀዘን",
      "indent": 24
    },
    {
      "text": "ደስታቸውን ዕልልታቸውንም ሰምቶ\nበገነት ምን ተድላ ደስታ ተገኝቶ",
      "indent": 0
    },
    {
      "text": "ይህን ያህል ዕልል ትላላችሁ ከቶ\nቢላቸው ከእግረ ገነት ቆይቶ",
      "indent": 24
    },
    {
      "text": "እንዲህ አሉት ጌታችን አዳም ደግ ሰው ነው\nወለድንና እያለብክ ጠጣን ብንለው",
      "indent": 0
    },
    {
      "text": "መለሰልን እንደዚህ ያለ ነገር\nምን አጥቼ ካንዲት ከበለስ በቀር",
      "indent": 24
    },
    {
      "text": "ሁሉ የኔ እኔ አዳምማ ጌታችሁ\nእናንተንስ ባላችሁበት ያርባችሁ",
      "indent": 0
    },
    {
      "text": "እናንተንም ባላችሁበት ያስባችሁ\nእንዳያርደን እንዳያልበንም ተጨንቆ",
      "indent": 24
    },
    {
      "text": "እንዲህ አርጎ ሰደደን እንጂ መርቆ\nስብሐት ለአብ ወወልድ ወመንፈስ ቅዱስ",
      "indent": 0
    },
    {
      "text": "ለዓለም እስከ ዘለዓለም ድረስ",
      "indent": 24
    }
  ]
}